napari_parallel/__init__.py
napari_parallel/_reader.py
napari_parallel/_sample_data.py
napari_parallel/_widget.py
napari_parallel/_writer.py
napari_parallel/napari.yaml
napari_parallel/_tests/__init__.py
napari_parallel/_tests/test_reader.py
napari_parallel/_tests/test_sample_data.py
napari_parallel/_tests/test_widget.py
napari_parallel/_tests/test_writer.py
napari_parallel-0.0.2.dist-info/LICENSE
napari_parallel-0.0.2.dist-info/METADATA
napari_parallel-0.0.2.dist-info/WHEEL
napari_parallel-0.0.2.dist-info/entry_points.txt
napari_parallel-0.0.2.dist-info/top_level.txt
napari_parallel-0.0.2.dist-info/RECORD
